[{"failures":[],"tindex":0,"variableMapping":{"delsq":"org.apache.commons.math3.optimization.direct.BOBYQAOptimizer.ONE_OVER_TEN","state":"state","org.apache.commons.math3.optim.nonlinear.scalar.noderiv.BOBYQAOptimizer.ZERO":"vquad"},"name":"replace","transplant":{"position":"org.apache.commons.math3.optim.nonlinear.scalar.noderiv.BOBYQAOptimizer:1996","type":"CtIfImpl"},"type":"adrStmt","transplantationPoint":{"position":"org.apache.commons.math3.optimization.direct.BOBYQAOptimizer:1105","type":"CtIfImpl"},"status":-1},{"failures":[],"tindex":0,"variableMapping":{},"name":"replaceWittgenstein","transplant":{"position":"org.apache.commons.math3.util.FastMathLiteralArrays:110","type":"CtUnaryOperatorImpl"},"type":"adrStmt","transplantationPoint":{"position":"org.apache.commons.math3.optimization.direct.BOBYQAOptimizer:1105","type":"CtIfImpl"},"status":-2},{"failures":[],"tindex":0,"variableMapping":{},"name":"replaceReaction","transplant":{"position":"org.apache.commons.math3.optim.nonlinear.scalar.noderiv.BOBYQAOptimizer:2255","type":"CtIfImpl"},"type":"adrStmt","transplantationPoint":{"position":"org.apache.commons.math3.optimization.direct.BOBYQAOptimizer:1105","type":"CtIfImpl"},"status":-2},{"failures":[],"tindex":0,"variableMapping":{},"name":"replaceRandom","transplant":{"position":"org.apache.commons.math3.util.FastMathLiteralArrays:1959","type":"CtUnaryOperatorImpl"},"type":"adrStmt","transplantationPoint":{"position":"org.apache.commons.math3.optimization.direct.BOBYQAOptimizer:1105","type":"CtIfImpl"},"status":-2},{"failures":[],"tindex":0,"variableMapping":{"rdnext":"vquad","i":"state","rednew":"vquad","isav":"state"},"name":"add","transplant":{"position":"org.apache.commons.math3.optimization.direct.BOBYQAOptimizer:2158","type":"CtIfImpl"},"type":"adrStmt","transplantationPoint":{"position":"org.apache.commons.math3.optimization.direct.BOBYQAOptimizer:1105","type":"CtIfImpl"},"status":-1},{"failures":[],"tindex":0,"variableMapping":{},"name":"addWittgenstein","transplant":{"position":"org.apache.commons.math3.util.FastMathLiteralArrays:3689","type":"CtUnaryOperatorImpl"},"type":"adrStmt","transplantationPoint":{"position":"org.apache.commons.math3.optimization.direct.BOBYQAOptimizer:1105","type":"CtIfImpl"},"status":-2},{"failures":[],"tindex":0,"variableMapping":{},"name":"addReaction","transplant":{"position":"org.apache.commons.math3.linear.SingularValueDecomposition:391","type":"CtIfImpl"},"type":"adrStmt","transplantationPoint":{"position":"org.apache.commons.math3.optimization.direct.BOBYQAOptimizer:1105","type":"CtIfImpl"},"status":-2},{"failures":[],"tindex":0,"variableMapping":{},"name":"addRandom","transplant":{"position":"org.apache.commons.math3.stat.descriptive.moment.SemiVariance:334","type":"CtEnumImpl"},"type":"adrStmt","transplantationPoint":{"position":"org.apache.commons.math3.optimization.direct.BOBYQAOptimizer:1105","type":"CtIfImpl"},"status":-2},{"failures":[],"tindex":0,"name":"delete","type":"adrStmt","transplantationPoint":{"position":"org.apache.commons.math3.optimization.direct.BOBYQAOptimizer:1105","type":"CtIfImpl"},"status":-2},{"failures":[],"tindex":0,"variableMapping":{"trustRegionCenterInterpolationPointIndex":"row","k":"row"},"name":"replace","transplant":{"position":"org.apache.commons.math3.optimization.direct.BOBYQAOptimizer:769","type":"CtIfImpl"},"type":"adrStmt","transplantationPoint":{"position":"org.apache.commons.math3.linear.AbstractFieldMatrix:480","type":"CtInvocationImpl"},"status":-2},{"failures":[],"tindex":0,"variableMapping":{},"name":"replaceWittgenstein","transplant":{"position":"org.apache.commons.math3.util.FastMathLiteralArrays:895","type":"CtUnaryOperatorImpl"},"type":"adrStmt","transplantationPoint":{"position":"org.apache.commons.math3.linear.AbstractFieldMatrix:480","type":"CtInvocationImpl"},"status":-2},{"failures":[],"tindex":0,"variableMapping":{},"name":"replaceReaction","transplant":{"position":"org.apache.commons.math3.util.MultidimensionalCounter:228","type":"CtWhileImpl"},"type":"adrStmt","transplantationPoint":{"position":"org.apache.commons.math3.linear.AbstractFieldMatrix:480","type":"CtInvocationImpl"},"status":-2},{"failures":[],"tindex":0,"variableMapping":{},"name":"replaceRandom","transplant":{"position":"org.apache.commons.math3.util.FastMathLiteralArrays:5108","type":"CtUnaryOperatorImpl"},"type":"adrStmt","transplantationPoint":{"position":"org.apache.commons.math3.linear.AbstractFieldMatrix:480","type":"CtInvocationImpl"},"status":-2},{"failures":[],"tindex":0,"variableMapping":{"columns":"row","length":"nRows"},"name":"add","transplant":{"position":"org.apache.commons.math3.linear.BlockFieldMatrix:219","type":"CtIfImpl"},"type":"adrStmt","transplantationPoint":{"position":"org.apache.commons.math3.linear.AbstractFieldMatrix:480","type":"CtInvocationImpl"},"status":-1},{"failures":[],"tindex":0,"variableMapping":{},"name":"addWittgenstein","transplant":{"position":"org.apache.commons.math3.util.FastMathLiteralArrays:5473","type":"CtUnaryOperatorImpl"},"type":"adrStmt","transplantationPoint":{"position":"org.apache.commons.math3.linear.AbstractFieldMatrix:480","type":"CtInvocationImpl"},"status":-2},{"failures":[],"tindex":0,"variableMapping":{},"name":"addReaction","transplant":{"position":"org.apache.commons.math3.util.ResizableDoubleArray:963","type":"CtIfImpl"},"type":"adrStmt","transplantationPoint":{"position":"org.apache.commons.math3.linear.AbstractFieldMatrix:480","type":"CtInvocationImpl"},"status":-2},{"failures":[],"tindex":0,"variableMapping":{},"name":"addRandom","transplant":{"position":"org.apache.commons.math3.dfp.Dfp:1114","type":"CtIfImpl"},"type":"adrStmt","transplantationPoint":{"position":"org.apache.commons.math3.linear.AbstractFieldMatrix:480","type":"CtInvocationImpl"},"status":-2},{"failures":[],"tindex":0,"name":"delete","type":"adrStmt","transplantationPoint":{"position":"org.apache.commons.math3.linear.AbstractFieldMatrix:480","type":"CtInvocationImpl"},"status":-2},{"failures":[],"tindex":0,"variableMapping":{"x":"ba","y":"main"},"name":"replace","transplant":{"position":"org.apache.commons.math3.stat.regression.AbstractMultipleLinearRegression:226","type":"CtIfImpl"},"type":"adrStmt","transplantationPoint":{"position":"org.apache.commons.math3.linear.BiDiagonalTransformer:151","type":"CtIfImpl"},"status":-1},{"failures":[],"tindex":0,"variableMapping":{},"name":"replaceWittgenstein","transplant":{"position":"org.apache.commons.math3.util.FastMathLiteralArrays:5476","type":"CtUnaryOperatorImpl"},"type":"adrStmt","transplantationPoint":{"position":"org.apache.commons.math3.linear.BiDiagonalTransformer:151","type":"CtIfImpl"},"status":-2},{"failures":[],"tindex":0,"variableMapping":{},"name":"replaceReaction","transplant":{"position":"org.apache.commons.math3.linear.CholeskyDecomposition:151","type":"CtForImpl"},"type":"adrStmt","transplantationPoint":{"position":"org.apache.commons.math3.linear.BiDiagonalTransformer:151","type":"CtIfImpl"},"status":-2},{"failures":[],"tindex":0,"variableMapping":{},"name":"replaceRandom","transplant":{"position":"org.apache.commons.math3.fraction.BigFraction:1037","type":"CtLocalVariableImpl"},"type":"adrStmt","transplantationPoint":{"position":"org.apache.commons.math3.linear.BiDiagonalTransformer:151","type":"CtIfImpl"},"status":-2},{"failures":[],"tindex":0,"variableMapping":{"hK":"secondary","k":"length","va":"ba","diagonal":"main","n":"length","diagOffset":"length"},"name":"add","transplant":{"position":"org.apache.commons.math3.linear.BiDiagonalTransformer:190","type":"CtForImpl"},"type":"adrStmt","transplantationPoint":{"position":"org.apache.commons.math3.linear.BiDiagonalTransformer:151","type":"CtIfImpl"},"status":-2},{"failures":[],"tindex":0,"variableMapping":{},"name":"addWittgenstein","transplant":{"position":"org.apache.commons.math3.util.FastMathLiteralArrays:1169","type":"CtUnaryOperatorImpl"},"type":"adrStmt","transplantationPoint":{"position":"org.apache.commons.math3.linear.BiDiagonalTransformer:151","type":"CtIfImpl"},"status":-2},{"failures":[],"tindex":0,"variableMapping":{},"name":"addReaction","transplant":{"position":"org.apache.commons.math3.analysis.differentiation.DSCompiler:1633","type":"CtIfImpl"},"type":"adrStmt","transplantationPoint":{"position":"org.apache.commons.math3.linear.BiDiagonalTransformer:151","type":"CtIfImpl"},"status":-2},{"failures":[],"tindex":0,"variableMapping":{},"name":"addRandom","transplant":{"position":"org.apache.commons.math3.distribution.ExponentialDistribution:301","type":"CtReturnImpl"},"type":"adrStmt","transplantationPoint":{"position":"org.apache.commons.math3.linear.BiDiagonalTransformer:151","type":"CtIfImpl"},"status":-2},{"failures":[],"tindex":0,"name":"delete","type":"adrStmt","transplantationPoint":{"position":"org.apache.commons.math3.linear.BiDiagonalTransformer:151","type":"CtIfImpl"},"status":-2},{"failures":[],"tindex":0,"variableMapping":{},"name":"replace","transplant":{"position":"org.apache.commons.math3.util.FastMathLiteralArrays:3178","type":"CtUnaryOperatorImpl"},"type":"adrStmt","transplantationPoint":{"position":"org.apache.commons.math3.util.FastMathLiteralArrays:5684","type":"CtUnaryOperatorImpl"},"status":-2},{"failures":[],"tindex":0,"variableMapping":{},"name":"replaceWittgenstein","transplant":{"position":"org.apache.commons.math3.util.FastMathLiteralArrays:425","type":"CtUnaryOperatorImpl"},"type":"adrStmt","transplantationPoint":{"position":"org.apache.commons.math3.util.FastMathLiteralArrays:5684","type":"CtUnaryOperatorImpl"},"status":-2},{"failures":[],"tindex":0,"variableMapping":{},"name":"replaceReaction","transplant":{"position":"org.apache.commons.math3.special.Beta:93","type":"CtUnaryOperatorImpl"},"type":"adrStmt","transplantationPoint":{"position":"org.apache.commons.math3.util.FastMathLiteralArrays:5684","type":"CtUnaryOperatorImpl"},"status":-2},{"failures":[],"tindex":0,"variableMapping":{},"name":"replaceRandom","transplant":{"position":"org.apache.commons.math3.dfp.DfpMath:170","type":"CtAssignmentImpl"},"type":"adrStmt","transplantationPoint":{"position":"org.apache.commons.math3.util.FastMathLiteralArrays:5684","type":"CtUnaryOperatorImpl"},"status":-2},{"failures":[],"tindex":0,"variableMapping":{},"name":"add","transplant":{"position":"org.apache.commons.math3.util.FastMathLiteralArrays:5764","type":"CtUnaryOperatorImpl"},"type":"adrStmt","transplantationPoint":{"position":"org.apache.commons.math3.util.FastMathLiteralArrays:5684","type":"CtUnaryOperatorImpl"},"status":-2},{"failures":[],"tindex":0,"variableMapping":{},"name":"addWittgenstein","transplant":{"position":"org.apache.commons.math3.util.FastMathLiteralArrays:479","type":"CtUnaryOperatorImpl"},"type":"adrStmt","transplantationPoint":{"position":"org.apache.commons.math3.util.FastMathLiteralArrays:5684","type":"CtUnaryOperatorImpl"},"status":-2},{"failures":[],"tindex":0,"variableMapping":{},"name":"addReaction","transplant":{"position":"org.apache.commons.math3.util.FastMathLiteralArrays:3488","type":"CtUnaryOperatorImpl"},"type":"adrStmt","transplantationPoint":{"position":"org.apache.commons.math3.util.FastMathLiteralArrays:5684","type":"CtUnaryOperatorImpl"},"status":-2},{"failures":[],"tindex":0,"variableMapping":{},"name":"addRandom","transplant":{"position":"org.apache.commons.math3.optimization.direct.CMAESOptimizer:748","type":"CtAssignmentImpl"},"type":"adrStmt","transplantationPoint":{"position":"org.apache.commons.math3.util.FastMathLiteralArrays:5684","type":"CtUnaryOperatorImpl"},"status":-2},{"failures":[],"tindex":0,"name":"delete","type":"adrStmt","transplantationPoint":{"position":"org.apache.commons.math3.util.FastMathLiteralArrays:5684","type":"CtUnaryOperatorImpl"},"status":-2},{"failures":[],"tindex":0,"variableMapping":{"param":"dataI"},"name":"replace","transplant":{"position":"org.apache.commons.math3.analysis.function.Gaussian:191","type":"CtIfImpl"},"type":"adrStmt","transplantationPoint":{"position":"org.apache.commons.math3.transform.FastFourierTransformer:173","type":"CtIfImpl"},"status":-1},{"failures":[],"tindex":0,"variableMapping":{},"name":"replaceWittgenstein","transplant":{"position":"org.apache.commons.math3.util.FastMathLiteralArrays:5679","type":"CtUnaryOperatorImpl"},"type":"adrStmt","transplantationPoint":{"position":"org.apache.commons.math3.transform.FastFourierTransformer:173","type":"CtIfImpl"},"status":-2},{"failures":[],"tindex":0,"variableMapping":{},"name":"replaceReaction","transplant":{"position":"org.apache.commons.math3.analysis.differentiation.DSCompiler:1361","type":"CtIfImpl"},"type":"adrStmt","transplantationPoint":{"position":"org.apache.commons.math3.transform.FastFourierTransformer:173","type":"CtIfImpl"},"status":-2},{"failures":[],"tindex":0,"variableMapping":{},"name":"replaceRandom","transplant":{"position":"org.apache.commons.math3.linear.SingularValueDecomposition:137","type":"CtLocalVariableImpl"},"type":"adrStmt","transplantationPoint":{"position":"org.apache.commons.math3.transform.FastFourierTransformer:173","type":"CtIfImpl"},"status":-1},{"failures":[],"tindex":0,"variableMapping":{"ntrits":"n","state":"n"},"name":"add","transplant":{"position":"org.apache.commons.math3.optimization.direct.BOBYQAOptimizer:1102","type":"CtIfImpl"},"type":"adrStmt","transplantationPoint":{"position":"org.apache.commons.math3.transform.FastFourierTransformer:173","type":"CtIfImpl"},"status":-2},{"failures":[],"tindex":0,"variableMapping":{},"name":"addWittgenstein","transplant":{"position":"org.apache.commons.math3.util.FastMathLiteralArrays:5729","type":"CtUnaryOperatorImpl"},"type":"adrStmt","transplantationPoint":{"position":"org.apache.commons.math3.transform.FastFourierTransformer:173","type":"CtIfImpl"},"status":-2},{"failures":[],"tindex":0,"variableMapping":{},"name":"addReaction","transplant":{"position":"org.apache.commons.math3.optimization.general.LevenbergMarquardtOptimizer:802","type":"CtIfImpl"},"type":"adrStmt","transplantationPoint":{"position":"org.apache.commons.math3.transform.FastFourierTransformer:173","type":"CtIfImpl"},"status":-2},{"failures":[],"tindex":0,"variableMapping":{},"name":"addRandom","transplant":{"position":"org.apache.commons.math3.linear.RealVector:1341","type":"CtReturnImpl"},"type":"adrStmt","transplantationPoint":{"position":"org.apache.commons.math3.transform.FastFourierTransformer:173","type":"CtIfImpl"},"status":-2},{"failures":[],"tindex":0,"name":"delete","type":"adrStmt","transplantationPoint":{"position":"org.apache.commons.math3.transform.FastFourierTransformer:173","type":"CtIfImpl"},"status":-1},{"failureDictionary":{}},{"memory":2012,"os.arch":"amd64","os.name":"Linux","cpu":[{"core":2,"vendor":"AMD","model":"Opteron","mhz":2393},{"core":2,"vendor":"AMD","model":"Opteron","mhz":2393}],"os.version":"3.2.0-4-amd64"}]
