{"testDiff":[],"transformation":{"failures":[],"tindex":48,"variableMapping":{"wdsz":"n","this":"this","n":"n"},"series":0,"name":"add","transplant":{"position":"org.apache.commons.codec.language.Metaphone:244","type":"CtIfImpl","sourcecode":"if (org.apache.commons.codec.language.Metaphone.isLastChar(int, int)) {\n    break;\n} "},"type":"adrStmt","transplantationPoint":{"position":"org.apache.commons.codec.language.Metaphone:179","type":"CtIfImpl","sourcecode":"if (org.apache.commons.codec.language.Metaphone.regionMatch(java.lang.StringBuilder, int, \"CIA\")) {\n    java.lang.StringBuilder.append('X');\n    break;\n} "},"status":0}}