{"failureDictionary":{"org.apache.commons.collections4.iterators.UnmodifiableOrderedMapIteratorTest.testMapIteratorOrder":36,"org.apache.commons.collections4.collection.SynchronizedCollectionTest.testCollectionToArray2":33,"org.apache.commons.collections4.list.SetUniqueListTest.testListEquals":13,"org.apache.commons.collections4.list.SetUniqueListTest.testSubListIsUnmodifiable":6,"org.apache.commons.collections4.bidimap.UnmodifiableSortedBidiMapTest.testBidiMapIteratorSet":34,"org.apache.commons.collections4.list.SetUniqueListTest.testCollectionRetainAll":27,"org.apache.commons.collections4.iterators.UnmodifiableOrderedMapIteratorTest.testMapIteratorSet":38,"org.apache.commons.collections4.bag.SynchronizedBagTest.testCollectionToArray2":32,"org.apache.commons.collections4.list.SetUniqueListTest.testListListIteratorByIndex":14,"org.apache.commons.collections4.list.SetUniqueListTest.testCollectionContains":25,"org.apache.commons.collections4.bidimap.UnmodifiableOrderedBidiMapTest.testBidiMapIteratorSet":35,"org.apache.commons.collections4.list.SetUniqueListTest.testCollectionSize":23,"org.apache.commons.collections4.list.SetUniqueListTest.testCollectionIterator":30,"org.apache.commons.collections4.list.SetUniqueListTest.testCollectionContainsAll":21,"org.apache.commons.collections4.list.SetUniqueListTest.testCollectionIteratorRemove":2,"org.apache.commons.collections4.list.SetUniqueListTest.testFactory":0,"org.apache.commons.collections4.list.SetUniqueListTest.testCollectionRemove":28,"org.apache.commons.collections4.bag.SynchronizedBagTest.testBagToArrayPopulate":31,"org.apache.commons.collections4.iterators.UnmodifiableOrderedMapIteratorTest.testRemove":39,"org.apache.commons.collections4.list.SetUniqueListTest.testListHashCode":11,"org.apache.commons.collections4.list.SetUniqueListTest.testListAddByIndex":12,"org.apache.commons.collections4.list.SetUniqueListTest.testListSetByIndex":5,"org.apache.commons.collections4.list.SetUniqueListTest.testCollectionIsEmpty":26,"org.apache.commons.collections4.list.SetUniqueListTest.testListGetByIndex":10,"org.apache.commons.collections4.list.SetUniqueListTest.testCollectionToArray":29,"org.apache.commons.collections4.list.SetUniqueListTest.testAddAll":9,"org.apache.commons.collections4.bag.UnmodifiableSortedBagTest.testCollectionContainsAll":44,"org.apache.commons.collections4.list.SetUniqueListTest.testCollectionRemoveAll":24,"org.apache.commons.collections4.iterators.UnmodifiableOrderedMapIteratorTest.testFullIterator":40,"org.apache.commons.collections4.list.SetUniqueListTest.testListLastIndexOf":19,"org.apache.commons.collections4.list.SetUniqueListTest.testCollectionAddAll":7,"org.apache.commons.collections4.list.SetUniqueListTest.testFullListSerialization":16,"org.apache.commons.collections4.list.SetUniqueListTest.testListIndexOf":18,"org.apache.commons.collections4.bag.PredicatedSortedBagTest.testCollectionContainsAll":42,"org.apache.commons.collections4.bag.CollectionSortedBagTest.testCollectionContainsAll":43,"org.apache.commons.collections4.list.SetUniqueListTest.testListIteratorAdd":3,"org.apache.commons.collections4.list.SetUniqueListTest.testRetainAllWithInitialList":1,"org.apache.commons.collections4.list.SetUniqueListTest.testListIteratorSet":4,"org.apache.commons.collections4.bag.TransformedSortedBagTest.testCollectionContainsAll":45,"org.apache.commons.collections4.list.SetUniqueListTest.testIntCollectionAddAll":8,"org.apache.commons.collections4.list.SetUniqueListTest.testListListIterator":15,"org.apache.commons.collections4.bag.TreeBagTest.testCollectionContainsAll":46,"org.apache.commons.collections4.list.SetUniqueListTest.testListRemoveByIndex":17,"org.apache.commons.collections4.iterators.UnmodifiableOrderedMapIteratorTest.testFullMapIterator":37,"org.apache.commons.collections4.list.SetUniqueListTest.testFullListCompatibility":20,"org.apache.commons.collections4.list.SetUniqueListTest.testCollectionToArray2":22,"org.apache.commons.collections4.CollectionUtilsTest.collateException1":41},"transformations":[{"failures":[],"tindex":"fccbf74c-423a-11e5-a9f6-ddc6155bed8d","series":0,"name":"delete","type":"adrStmt","transplantationPoint":{"position":"org.apache.commons.collections4.ListUtils:107","type":"CtReturnImpl","sourcecode":"return java.util.List<E>"},"status":-2},{"failures":[],"tindex":"fccbf74d-423a-11e5-a9f6-11a713bd598c","series":0,"name":"replace","transplant":{"position":"org.apache.commons.collections4.map.AbstractHashedMap:824","type":"CtReturnImpl","sourcecode":"return org.apache.commons.collections4.iterators.EmptyIterator.<java.util.Map.Entry<K, V>>emptyIterator()"},"variableMap":{},"type":"adrStmt","transplantationPoint":{"position":"org.apache.commons.collections4.collection.UnmodifiableBoundedCollection:117","type":"CtReturnImpl","sourcecode":"return org.apache.commons.collections4.iterators.UnmodifiableIterator.unmodifiableIterator(org.apache.commons.collections4.collection.UnmodifiableBoundedCollection<E>.decorated().iterator())"},"status":-2},{"failures":[0,1,2,3,4,5,6,7,8,9,10,11,12,13,14,15,16,17,18,19,20,21,22,23,24,25,26,27,28,29,30],"tindex":"fccc1e5e-423a-11e5-a9f6-e774d4f0f05a","series":0,"name":"replace","transplant":{"position":"org.apache.commons.collections4.iterators.ArrayIterator:135","type":"CtReturnImpl","sourcecode":"return (int) < (int)"},"variableMap":{"endIndex":"index","index":"index"},"type":"adrStmt","transplantationPoint":{"position":"org.apache.commons.collections4.list.AbstractListDecorator:75","type":"CtReturnImpl","sourcecode":"return org.apache.commons.collections4.list.AbstractListDecorator<E>.decorated().addAll(int, java.util.Collection<? extends E>)"},"status":-1},{"failures":[31,32,33],"tindex":"fccc1e5f-423a-11e5-a9f6-5f42d37ba8e9","series":0,"name":"replace","transplant":{"position":"org.apache.commons.collections4.map.AbstractInputCheckedMapDecorator:153","type":"CtReturnImpl","sourcecode":"return ((T[])(java.lang.Object[]))"},"variableMap":{"result":"lock"},"type":"adrStmt","transplantationPoint":{"position":"org.apache.commons.collections4.collection.SynchronizedCollection:163","type":"CtSynchronizedImpl","sourcecode":"synchronized(java.lang.Object) {\n    return org.apache.commons.collections4.collection.SynchronizedCollection<E>.decorated().toArray(T[]);\n}"},"status":-1},{"failures":[34,35,36,37,38,39,40],"tindex":"fccc1e60-423a-11e5-a9f6-b9813cf292c5","series":0,"name":"replace","transplant":{"position":"org.apache.commons.collections4.map.AbstractHashedMap:858","type":"CtReturnImpl","sourcecode":"return false"},"variableMap":{},"type":"adrStmt","transplantationPoint":{"position":"org.apache.commons.collections4.iterators.UnmodifiableOrderedMapIterator:73","type":"CtReturnImpl","sourcecode":"return org.apache.commons.collections4.OrderedMapIterator<? extends K, ? extends V>.hasNext()"},"status":-1},{"failures":[],"tindex":"fccc1e61-423a-11e5-a9f6-0db1118e0a26","series":0,"name":"replace","transplant":{"position":"org.apache.commons.collections4.map.StaticBucketMap:662","type":"CtReturnImpl","sourcecode":"return new org.apache.commons.collections4.map.StaticBucketMap.ValueIterator()"},"variableMap":{},"type":"adrStmt","transplantationPoint":{"position":"org.apache.commons.collections4.map.AbstractLinkedMap:470","type":"CtReturnImpl","sourcecode":"return new org.apache.commons.collections4.map.AbstractLinkedMap.ValuesIterator<V>(this)"},"status":-2},{"failures":[41],"tindex":"fccc1e62-423a-11e5-a9f6-bd44668f3b94","series":0,"name":"replace","transplant":{"position":"org.apache.commons.collections4.list.AbstractLinkedList:842","type":"CtThrowImpl","sourcecode":"throw new java.util.NoSuchElementException(\"Already at start of list.\")"},"variableMap":{},"type":"adrStmt","transplantationPoint":{"position":"org.apache.commons.collections4.CollectionUtils:1592","type":"CtThrowImpl","sourcecode":"throw new java.lang.IllegalArgumentException(\"The collections must not be null\")"},"status":-1},{"failures":[],"tindex":"fccc1e63-423a-11e5-a9f6-cdc92cd63411","series":0,"name":"add","transplant":{"position":"org.apache.commons.collections4.bidimap.TreeBidiMap:2054","type":"CtReturnImpl","sourcecode":"return org.apache.commons.collections4.bidimap.TreeBidiMap.this.isEmpty()"},"variableMap":{},"type":"adrStmt","transplantationPoint":{"position":"org.apache.commons.collections4.comparators.TransformingComparator:116","type":"CtReturnImpl","sourcecode":"return true"},"status":-2},{"failures":[],"tindex":"fccc4574-423a-11e5-a9f6-83cc318da3f0","series":0,"name":"replace","transplant":{"position":"org.apache.commons.collections4.bidimap.TreeBidiMap:683","type":"CtIfImpl","sourcecode":"if (org.apache.commons.collections4.bidimap.TreeBidiMap.Node<K, V> != null) {\n    while ((org.apache.commons.collections4.bidimap.TreeBidiMap.Node<K, V>.getLeft(org.apache.commons.collections4.bidimap.TreeBidiMap.DataElement)) != null) {\n        org.apache.commons.collections4.bidimap.TreeBidiMap.Node<K, V> = org.apache.commons.collections4.bidimap.TreeBidiMap.Node<K, V>.getLeft(org.apache.commons.collections4.bidimap.TreeBidiMap.DataElement);\n    }\n} "},"variableMap":{"rval":"currentNode","dataElement":"dataElement"},"type":"adrStmt","transplantationPoint":{"position":"org.apache.commons.collections4.bidimap.TreeBidiMap:1047","type":"CtInvocationImpl","sourcecode":"org.apache.commons.collections4.bidimap.TreeBidiMap<K, V>.rotateLeft(org.apache.commons.collections4.bidimap.TreeBidiMap<K, V>.getParent(org.apache.commons.collections4.bidimap.TreeBidiMap.Node<K, V>, org.apache.commons.collections4.bidimap.TreeBidiMap.DataElement), org.apache.commons.collections4.bidimap.TreeBidiMap.DataElement)"},"status":0},{"failures":[],"tindex":"fccc4575-423a-11e5-a9f6-e18b0480fdf4","series":0,"name":"replace","transplant":{"position":"org.apache.commons.collections4.iterators.CollatingIterator:282","type":"CtIfImpl","sourcecode":"if ((int) == (-1)) {\n    throw new java.lang.IllegalStateException(\"No value has been returned yet\");\n} "},"variableMap":{"lastReturned":"index"},"type":"adrStmt","transplantationPoint":{"position":"org.apache.commons.collections4.map.AbstractLinkedMap:236","type":"CtIfImpl","sourcecode":"if (int < ((int) / 2)) {\n    org.apache.commons.collections4.map.AbstractLinkedMap.LinkEntry<K, V> = org.apache.commons.collections4.map.AbstractLinkedMap.LinkEntry<K, V>.org.apache.commons.collections4.map.AbstractLinkedMap.LinkEntry<K, V>;\n    for (int int = 0 ; int < int ; int++) {\n        org.apache.commons.collections4.map.AbstractLinkedMap.LinkEntry<K, V> = org.apache.commons.collections4.map.AbstractLinkedMap.LinkEntry<K, V>.org.apache.commons.collections4.map.AbstractLinkedMap.LinkEntry<K, V>;\n    }\n} else {\n    org.apache.commons.collections4.map.AbstractLinkedMap.LinkEntry<K, V> = org.apache.commons.collections4.map.AbstractLinkedMap.LinkEntry<K, V>;\n    for (int int = int ; int > int ; int--) {\n        org.apache.commons.collections4.map.AbstractLinkedMap.LinkEntry<K, V> = org.apache.commons.collections4.map.AbstractLinkedMap.LinkEntry<K, V>.org.apache.commons.collections4.map.AbstractLinkedMap.LinkEntry<K, V>;\n    }\n}"},"status":-2},{"failures":[],"tindex":"fccc4576-423a-11e5-a9f6-913c7a82dae3","series":0,"name":"delete","type":"adrStmt","transplantationPoint":{"position":"org.apache.commons.collections4.set.ListOrderedSet:230","type":"CtLocalVariableImpl","sourcecode":"final java.util.Set<java.lang.Object> java.util.Set<java.lang.Object> = new java.util.HashSet<java.lang.Object>()"},"status":-2},{"failures":[],"tindex":"fccc4577-423a-11e5-a9f6-e3529b3866cf","series":0,"name":"add","transplant":{"position":"org.apache.commons.collections4.CollectionUtils:1444","type":"CtAssignmentImpl","sourcecode":"java.lang.Object[][int] = java.lang.Object[][int]"},"variableMap":{"array":"tmp","i":"j","j":"j"},"type":"adrStmt","transplantationPoint":{"position":"org.apache.commons.collections4.CollectionUtils:1443","type":"CtAssignmentImpl","sourcecode":"java.lang.Object = java.lang.Object[][int]"},"status":-2},{"failures":[],"tindex":"fccc4578-423a-11e5-a9f6-7b6ef651a62c","series":0,"name":"replace","transplant":{"position":"org.apache.commons.collections4.trie.AbstractPatriciaTrie:1978","type":"CtLocalVariableImpl","sourcecode":"org.apache.commons.collections4.trie.AbstractPatriciaTrie.TrieEntry<K, V> org.apache.commons.collections4.trie.AbstractPatriciaTrie.TrieEntry<K, V> = null"},"variableMap":{},"type":"adrStmt","transplantationPoint":{"position":"org.apache.commons.collections4.trie.AbstractPatriciaTrie:788","type":"CtLocalVariableImpl","sourcecode":"final org.apache.commons.collections4.trie.AbstractPatriciaTrie.TrieEntry<K, V> org.apache.commons.collections4.trie.AbstractPatriciaTrie.TrieEntry<K, V> = org.apache.commons.collections4.trie.AbstractPatriciaTrie<K, V>.lastEntry()"},"status":-2},{"failures":[],"tindex":"fccc6c89-423a-11e5-a9f6-d10843245ed5","series":0,"name":"replace","transplant":{"position":"org.apache.commons.collections4.bidimap.TreeBidiMap:2054","type":"CtReturnImpl","sourcecode":"return org.apache.commons.collections4.bidimap.TreeBidiMap.this.isEmpty()"},"variableMap":{},"type":"adrStmt","transplantationPoint":{"position":"org.apache.commons.collections4.map.MultiKeyMap:750","type":"CtReturnImpl","sourcecode":"return boolean"},"status":-2},{"failures":[],"tindex":"fccc6c8a-423a-11e5-a9f6-8914a48bb209","series":0,"name":"replace","transplant":{"position":"org.apache.commons.collections4.trie.AbstractPatriciaTrie:1569","type":"CtLocalVariableImpl","sourcecode":"final org.apache.commons.collections4.trie.AbstractPatriciaTrie.TrieEntry<K, V> org.apache.commons.collections4.trie.AbstractPatriciaTrie.TrieEntry<K, V> = org.apache.commons.collections4.trie.AbstractPatriciaTrie.TrieEntry<K, V>"},"variableMap":{"next":"left"},"type":"adrStmt","transplantationPoint":{"position":"org.apache.commons.collections4.trie.AbstractPatriciaTrie:457","type":"CtLocalVariableImpl","sourcecode":"org.apache.commons.collections4.trie.AbstractPatriciaTrie.TrieEntry<K, V> org.apache.commons.collections4.trie.AbstractPatriciaTrie.TrieEntry<K, V> = org.apache.commons.collections4.trie.AbstractPatriciaTrie.TrieEntry<K, V>.org.apache.commons.collections4.trie.AbstractPatriciaTrie.TrieEntry<K, V>"},"status":-2},{"failures":[],"tindex":"fccc6c8b-423a-11e5-a9f6-4559f85c020a","series":0,"name":"replace","transplant":{"position":"org.apache.commons.collections4.queue.CircularFifoQueue:310","type":"CtIfImpl","sourcecode":"if ((int) >= (int)) {\n    int = 0;\n} "},"variableMap":{"start":"index","maxElements":"index"},"type":"adrStmt","transplantationPoint":{"position":"org.apache.commons.collections4.list.TreeList:260","type":"CtInvocationImpl","sourcecode":"org.apache.commons.collections4.list.TreeList<E>.checkInterval(int, 0, (org.apache.commons.collections4.list.TreeList<E>.(size()) - 1))"},"status":-2},{"failures":[],"tindex":"fccc6c8c-423a-11e5-a9f6-a5485f4b8b1a","series":0,"name":"add","transplant":{"position":"org.apache.commons.collections4.map.MultiKeyMap:203","type":"CtLocalVariableImpl","sourcecode":"org.apache.commons.collections4.map.AbstractHashedMap.HashEntry<org.apache.commons.collections4.keyvalue.MultiKey<? extends K>, V> org.apache.commons.collections4.map.AbstractHashedMap.HashEntry<org.apache.commons.collections4.keyvalue.MultiKey<? extends K>, V> = null"},"variableMap":{},"type":"adrStmt","transplantationPoint":{"position":"org.apache.commons.collections4.map.MultiKeyMap:202","type":"CtLocalVariableImpl","sourcecode":"org.apache.commons.collections4.map.AbstractHashedMap.HashEntry<org.apache.commons.collections4.keyvalue.MultiKey<? extends K>, V> org.apache.commons.collections4.map.AbstractHashedMap.HashEntry<org.apache.commons.collections4.keyvalue.MultiKey<? extends K>, V> = org.apache.commons.collections4.map.MultiKeyMap<K, V>.decorated().org.apache.commons.collections4.map.AbstractHashedMap.HashEntry<org.apache.commons.collections4.keyvalue.MultiKey<? extends K>, V>[][int]"},"status":-2},{"failures":[],"tindex":"fccc6c8d-423a-11e5-a9f6-31837c6bb821","series":0,"name":"add","transplant":{"position":"org.apache.commons.collections4.set.UnmodifiableSortedSet:57","type":"CtReturnImpl","sourcecode":"return java.util.SortedSet<E>"},"variableMap":{"set":"sub"},"type":"adrStmt","transplantationPoint":{"position":"org.apache.commons.collections4.set.UnmodifiableSortedSet:138","type":"CtReturnImpl","sourcecode":"return new org.apache.commons.collections4.set.UnmodifiableSortedSet<E>(java.util.SortedSet<E>)"},"status":-2},{"failures":[42,43,44,45,46],"tindex":"fccc6c8e-423a-11e5-a9f6-bfc125b770ce","series":0,"name":"add","transplant":{"position":"org.apache.commons.collections4.bag.CollectionBag:95","type":"CtIfImpl","sourcecode":"if (!org.apache.commons.collections4.collection.AbstractCollectionDecorator<E>.(contains(java.util.Iterator<?>.next()))) {\n    return false;\n} "},"variableMap":{"e":"e","this":"this"},"type":"adrStmt","transplantationPoint":{"position":"org.apache.commons.collections4.bag.CollectionSortedBag:94","type":"CtWhileImpl","sourcecode":"while (java.util.Iterator<?>.hasNext()) {\n    if (!org.apache.commons.collections4.collection.AbstractCollectionDecorator<E>.(contains(java.util.Iterator<?>.next()))) {\n        return false;\n    } \n}"},"status":-1},{"failures":[],"tindex":"fccc939f-423a-11e5-a9f6-494ef35239fd","series":0,"name":"add","transplant":{"position":"org.apache.commons.collections4.map.UnmodifiableSortedMap:61","type":"CtIfImpl","sourcecode":"if (java.util.SortedMap<K, ? extends V> instanceof org.apache.commons.collections4.Unmodifiable) {\n    @java.lang.SuppressWarnings(value = \"unchecked\")\n    final java.util.SortedMap<K, V> java.util.SortedMap<K, V> = ((java.util.SortedMap<K, V>)(java.util.SortedMap<K, ? extends V>));\n    return java.util.SortedMap<K, V>;\n} "},"variableMap":{"map":"map"},"type":"adrStmt","transplantationPoint":{"position":"org.apache.commons.collections4.map.UnmodifiableSortedMap:66","type":"CtReturnImpl","sourcecode":"return new org.apache.commons.collections4.map.UnmodifiableSortedMap<K, V>(java.util.SortedMap<K, ? extends V>)"},"status":-2}],"header":{"groupId":"org.apache.commons","transformationCount":20,"projectType":"maven","artifactId":"commons-collections4","generatorVersion":"1.0","version":"4.0"}}